ProBEX/__init__.py
ProBEX/add_Scripts.py
ProBEX/run_all.py
ProBEX/__pycache__/__init__.cpython-312.pyc
ProBEX/__pycache__/run_all.cpython-312.pyc
ProBEX/scripts/__init__.py
ProBEX/scripts/GATA4_scripts/SNPscore_memePWM_logo_with_bars.py
ProBEX/scripts/GATA4_scripts/__init__.py
ProBEX/scripts/GATA4_scripts/combine_data_lib_unb_bound_v2.py
ProBEX/scripts/GATA4_scripts/combine_data_lib_unb_bound_with_psuedocounts_2point5perM_for_unbound.py
ProBEX/scripts/GATA4_scripts/combine_data_with_zeronM_lib_unb_bound_with_psuedocounts_2point5perM_for_unbound.py
ProBEX/scripts/GATA4_scripts/corr_plot_btw_rep.py
ProBEX/scripts/GATA4_scripts/corr_plot_btw_rep_with_accepted_rsIDs.py
ProBEX/scripts/GATA4_scripts/corr_scatter_3000nM_R1_R2.py
ProBEX/scripts/GATA4_scripts/create_heatmap_for_controls.py
ProBEX/scripts/GATA4_scripts/extract_columns_withparameters.py
ProBEX/scripts/GATA4_scripts/extract_increased_decreased_rsIDs_from_scatterplot.py
ProBEX/scripts/GATA4_scripts/extract_increased_decreased_rsIDs_from_scatterplot_foreach_conc.py
ProBEX/scripts/GATA4_scripts/extract_tables_foreach_conc_scatter.py
ProBEX/scripts/GATA4_scripts/extract_top_K_values_for_MEME_LSGKM.py
ProBEX/scripts/GATA4_scripts/fitting_poisson_eQ_2_also_withUnb_with_bi.py
ProBEX/scripts/GATA4_scripts/gen_motifs_pdf_from_meme.py
ProBEX/scripts/GATA4_scripts/generate_mean_heatmap_from_scatter.py
ProBEX/scripts/GATA4_scripts/generate_mean_heatmap_from_scatter_for_eachConc.py
ProBEX/scripts/GATA4_scripts/get_AT_GC_percent_withfitted_C_denom.py
ProBEX/scripts/GATA4_scripts/get_enrichment_calc_bound_lib.py
ProBEX/scripts/GATA4_scripts/get_enrichment_calc_bound_unb.py
ProBEX/scripts/GATA4_scripts/get_enrichment_calc_bound_unb_without_pseudocounts.py
ProBEX/scripts/GATA4_scripts/get_fasta_bed_files_v1.py
ProBEX/scripts/GATA4_scripts/get_fasta_bed_files_v2.py
ProBEX/scripts/GATA4_scripts/get_thedenominators_iteratively.py
ProBEX/scripts/GATA4_scripts/getlist_accepted_discarded_rsIDs.py
probex_snp-0.1.1.dist-info/licenses/LICENSE
probex_snp-0.1.1.dist-info/METADATA
probex_snp-0.1.1.dist-info/WHEEL
probex_snp-0.1.1.dist-info/entry_points.txt
probex_snp-0.1.1.dist-info/top_level.txt
probex_snp-0.1.1.dist-info/RECORD
