Metadata-Version: 2.4
Name: ProBEX-snp
Version: 0.1.1
Summary: A tool for SNP-based Poisson binding analysis on SNP-bind-n-seq sequencing data
Home-page: https://github.com/Shreya-droid/SNPoiss_bind_n_seq
Author: Shreya Sharma, PhD student @IITR
Author-email: shreya_s@bt.iitr.ac.in
License: MIT
License-File: LICENSE
Requires-Dist: pandas>=1.3.5
Requires-Dist: numpy>=1.21.6
Requires-Dist: scikit-learn>=1.0.2
Requires-Dist: scipy>=1.7.3
Requires-Dist: matplotlib
Requires-Dist: seaborn
Requires-Dist: openpyxl
Requires-Dist: adjustText
Requires-Dist: jinja2
Requires-Dist: pylatex
Requires-Dist: psutil
Dynamic: author
Dynamic: author-email
Dynamic: home-page
Dynamic: license
Dynamic: license-file
Dynamic: requires-dist
Dynamic: summary
